pyglimmpse/NonCentralityDistribution.py
pyglimmpse/WeightedSumOfNoncentralChiSquaresDistribution.py
pyglimmpse/__init__.py
pyglimmpse/chisquareterm.py
pyglimmpse/constants.py
pyglimmpse/finv.py
pyglimmpse/input.py
pyglimmpse/multirep.py
pyglimmpse/orpol.py
pyglimmpse/probf.py
pyglimmpse/qprob.py
pyglimmpse/ranksymm.py
pyglimmpse/samplesize.py
pyglimmpse/unirep.py
pyglimmpse/validators.py
pyglimmpse/exceptions/__init__.py
pyglimmpse/exceptions/glimmpse_exception.py
pyglimmpse/model/__init__.py
pyglimmpse/model/epsilon.py
pyglimmpse/model/hypothesis_error.py
pyglimmpse/model/power.py
pyglimmpse/model/study_design.py
pyglimmpse-0.0.33.dist-info/METADATA
pyglimmpse-0.0.33.dist-info/RECORD
pyglimmpse-0.0.33.dist-info/WHEEL
pyglimmpse-0.0.33.dist-info/top_level.txt
