Metadata-Version: 2.1
Name: pyglimmpse
Version: 0.0.33
Summary: UNKNOWN
Home-page: UNKNOWN
Author: UNKNOWN
Author-email: UNKNOWN
License: UNKNOWN
Platform: UNKNOWN
Requires-Dist: scipy
Requires-Dist: numpy
